README.txt
setup.py
snehakvsearch.py
snehakvsearch.egg-info/PKG-INFO
snehakvsearch.egg-info/SOURCES.txt
snehakvsearch.egg-info/dependency_links.txt
snehakvsearch.egg-info/top_level.txt