Metadata-Version: 2.2
Name: snehakvsearch
Version: 1.3
Summary: The Head First Python Search Tools
Author: snehha S
Author-email: snehas0128@gmail.com
Dynamic: author
Dynamic: author-email
Dynamic: summary
